design/digital/I2C/i2c_controller.v
`timescale 1ns / 1ps
//////////////////////////////////////////////////////////////////////////////////
// Company: 
// Engineer: 
// 
// Create Date: 06/25/2026 01:09:04 AM
// Design Name: I2C Slave Controller Block
// Module Name: i2c_controller
// Project Name: 
// Target Devices: XC7Z010-CLG225-1 Zynq 7010
// Tool Versions: 
// Description: 
// 
// Dependencies: 
// 
// Revision:
// Revision 0.01 - File Created
// Additional Comments:
// 
//////////////////////////////////////////////////////////////////////////////////


module i2c_controller #(parameter WIDTH = 8) (
    input i2c_sda_in,
    output reg i2c_sda_out_pin_ctrl,
    output i2c_sda_out_pin_ctrl_n,
    input i2c_scl_in,
    input CLK_I,
    input RST_I,
    input [WIDTH-1:0] ADDR_I,
    input [WIDTH-1:0] DAT_I,
    output reg [WIDTH-1:0] DAT_O,
    input CYC_I,
    input STB_I,
    input WE_I,
    output reg ACK_O,
    output reg ERR_O,
    output reg RTY_O
    );

    // General Register that can be accessed through the bus
    // All registers are in MSB format
    // Contents : 
    // addr_set_register (0x0A) --> used to set what address we need the module to respond to.
    //      - 8 bit wide, but only bit 6 to 0 that is used.
    // recv_data_buffer (0x0B) --> used for WRITE process where we receive data
    //      - 8 bit wide, stored the received byte
    // send_data_buffer (0x0C) --> used for READ process where we send data
    //      - 8 bit wide, stored the outgoing byte
    // ctrl_status_register (0x0D) --> used to poll or set the operation of the module
    //      - bit 7: data received status, 1 means received data. Poll this to see if we receive data
    //      - bit 6: data send status, 1 means send data done, 0 means in progress
    //      - bit 5: I2C read request, 1 means we need to send data, 0 means no action needed 
    //      - bit 4: I2C mode (MASTER/SLAVE) (coming soon! we won't need this for now)
    //      - bit 3: I2C master speed (coming soon! we won't need this for now)
    //      - bit 2: Reserved
    //      - bit 1: Reserved
    //      - bit 0: Reserved

    // Registers of the I2C Blocks
    // The localparam is for defining the address of the I2C block's registers, please change it here in case
    // you need its address to be other than the default
    localparam [WIDTH-1:0] ADDR_SET_REGISTER_ADDRESS = 10;
    localparam [WIDTH-1:0] RECV_DATA_BUFFER_ADDRESS = 11;
    localparam [WIDTH-1:0] SEND_DATA_BUFFER_ADDRESS = 12;
    localparam [WIDTH-1:0] CTRL_STATUS_REGISTER_ADDRESS = 13;

    reg [7:0] addr_set_register;
    reg [7:0] recv_data_buffer;
    reg [7:0] send_data_buffer;
    reg [7:0] ctrl_status_register;

    // Wishbone Interface of the I2C block
    always @(posedge CLK_I) begin
        if (RST_I == 1'b1) begin
            // Reset everything!
            DAT_O <= 0;
            ERR_O <= 1'b0;
            ACK_O <= 1'b0;
            RTY_O <= 1'b0;
        end
        else if (RST_I == 1'b0 && CYC_I == 1'b1 && STB_I == 1'b1) begin
            if ((ACK_O | ERR_O | RTY_O) == 1'b0) begin
                case (ADDR_I)
                    ADDR_SET_REGISTER_ADDRESS : begin
                        if (WE_I == 1'b1) begin
                            addr_set_register <= DAT_I;
                            ACK_O <= 1'b1;
                            ERR_O <= 1'b0;
                            RTY_O <= 1'b0;
                        end
                        else begin
                            DAT_O <= addr_set_register;
                            ACK_O <= 1'b1;
                            ERR_O <= 1'b0;
                            RTY_O <= 1'b0;
                        end
                    end
                    RECV_DATA_BUFFER_ADDRESS : begin
                        if (WE_I == 1'b1) begin
                            // Throw ERR signal (receive buffer is read only!)
                            recv_data_buffer <= recv_data_buffer;
                            ACK_O <= 1'b0;
                            ERR_O <= 1'b1;
                            RTY_O <= 1'b0;
                        end
                        else begin
                            DAT_O <= recv_data_buffer;
                            ACK_O <= 1'b1;
                            ERR_O <= 1'b0;
                            RTY_O <= 1'b0;
                        end
                    end
                    SEND_DATA_BUFFER_ADDRESS : begin
                        if (WE_I == 1'b1) begin
                            send_data_buffer <= DAT_I;
                            ACK_O <= 1'b1;
                            ERR_O <= 1'b0;
                            RTY_O <= 1'b0;
                        end
                        else begin
                            DAT_O <= send_data_buffer;
                            ACK_O <= 1'b1;
                            ERR_O <= 1'b0;
                            RTY_O <= 1'b0;
                        end
                    end
                    CTRL_STATUS_REGISTER_ADDRESS : begin
                        if (WE_I == 1'b1) begin
                            ctrl_status_register <= DAT_I;
                            ACK_O <= 1'b1;
                            ERR_O <= 1'b0;
                            RTY_O <= 1'b0;
                        end
                        else begin
                            DAT_O <= ctrl_status_register;
                            ACK_O <= 1'b1;
                            ERR_O <= 1'b0;
                            RTY_O <= 1'b0;
                        end
                    end
                   default : begin
                        // Register does not exist, but do not throw any error
                        DAT_O <= 0;
                        ERR_O <= 1'b0;
                        ACK_O <= 1'b0;
                        RTY_O <= 1'b0;
                    end
                endcase
            end  
            // if any of the signaling has been asserted (ACK, RTY, or ERR)...
            else if ((ACK_O | ERR_O | RTY_O) == 1'b1) begin
                // de-assert first before moving on to the next transaction
                DAT_O <= 0;
                ERR_O <= 1'b0;
                ACK_O <= 1'b0;
                RTY_O <= 1'b0;
            end
        end
    end

    // Start-Stop condition detector
    reg sda_previous_state;
    wire start_condition;
    wire stop_condition;
    
    assign start_condition = sda_previous_state & ~i2c_sda_in & i2c_scl_in;
    assign stop_condition = ~sda_previous_state & i2c_sda_in & i2c_scl_in;
    always @(posedge CLK_I) begin
        if (RST_I == 1'b1) sda_previous_state <= 1'b0;
        else sda_previous_state <= i2c_sda_in;
    end

    // Rising-Falling edge detector
    reg previous_state;
    reg rising_edge_detected;
    reg falling_edge_detected;

    
    always @(posedge CLK_I) begin
        if (RST_I == 1'b1) previous_state <= 1'b0;
        else previous_state <= i2c_scl_in;

        rising_edge_detected <= ~previous_state & i2c_scl_in;
        falling_edge_detected <= previous_state & ~i2c_scl_in;
    end

    // I2C State Machine
    localparam STATE_IDLE = 2'b00;
    localparam STATE_ADDR = 2'b01;
    localparam STATE_READ = 2'b10;
    localparam STATE_WRITE = 2'b11;

    reg [1:0] i2c_state;
    wire [1:0] i2c_next_state;
    always @(posedge CLK_I) begin
        if (RST_I == 1'b1) i2c_state <= STATE_IDLE;
        else i2c_state <= i2c_next_state;
    end 

    // I2C: Subroutine IDLE 
    reg [1:0] i2c_next_state_idle_block;
    always @(*) begin
        if (start_condition == 1'b1 && i2c_state == STATE_IDLE) i2c_next_state_idle_block = STATE_ADDR;
        else i2c_next_state_idle_block = STATE_IDLE; 
    end

    // I2C: Subroutine ADDR, READ, WRITE in one iteration
    reg [1:0] i2c_next_state_routine_block;
    reg [3:0] iteration;
    reg [7:0] address_data_buffer_internal;
    reg [1:0] falling_edge_delayer;
    reg [3:0] iteration_write;
    
    wire falling_edge_detected_delayed;
    
    reg write_request_internal_flag;
    reg received_data_internal_flag;
    reg read_request_internal_flag;

    assign falling_edge_detected_delayed = falling_edge_delayer[1];

    always @(posedge CLK_I) begin
        if (RST_I == 1'b1) begin
            i2c_next_state_routine_block <= STATE_IDLE;
            iteration <= 4'd0;
            register_addr_data_flag <= 1'b0;
            register_content_data_flag <= 1'b0;
        end
        else if (stop_condition == 1'b1) begin
            i2c_next_state_routine_block <= STATE_IDLE;
            iteration <= 4'd0;
            register_addr_data_flag <= 1'b0;
            register_content_data_flag <= 1'b0;
        end
        else if (start_condition == 1'b1) begin
            i2c_next_state_routine_block <= STATE_ADDR;
            iteration <= 4'd0;
            register_addr_data_flag <= 1'b0;
            register_content_data_flag <= 1'b0;
        end
        else begin
            case(i2c_state)
                STATE_ADDR : begin
                    // Let's sample all the bits
                    if (rising_edge_detected == 1'b1 && iteration < 8) begin
                        // sample the data from sda input line
                        address_data_buffer_internal[7 - iteration] <= i2c_sda_in;
                        // increment the iteration counter to iterate through all bits
                        iteration <= iteration + 1'b1;
                        // keep the current state until the last bit
                        i2c_next_state_routine_block <= STATE_ADDR;
                    end
                    // When every bit has been sampled...
                    else if (rising_edge_detected == 1'b1 && iteration == 8) begin
                        // if the address is correct... (only 7-bit address is supported)
                        if (address_data_buffer_internal[7:1] == addr_set_register[7:1]) begin
                            // reset the subroutine FSM
                            iteration <= 4'd0;
                            // give the proper ACK to the line
                            i2c_sda_out_pin_ctrl <= 1'b0;
                            // the check the read/write bit
                            // if it's 1 (means I2C read command is received a.k.a requesting data --> must WRITE)...
                            if (address_data_buffer_internal[0] == 1) begin
                                i2c_next_state_routine_block <= STATE_WRITE;
                                write_request_internal_flag <= 1'b1;
                            end 
                            // if it's 0 (means I2C write command is received a.k.a receiving data --> must READ)...
                            else if (address_data_buffer_internal[0] == 0) begin
                                i2c_next_state_routine_block <= STATE_READ;
                                read_request_internal_flag <= 1'b1;
                            end
                        end else begin
                            // reset the subroutine FSM
                            iteration <= 4'd0;
                            // do not give the proper ACK to the line
                            i2c_sda_out_pin_ctrl <= 1'b0;
                            // return to IDLE state
                            i2c_next_state_routine_block <= STATE_IDLE;
                        end
                    end
                    else begin
                        // preserve current state
                        iteration <= iteration;
                        i2c_sda_out_pin_ctrl <= i2c_sda_out_pin_ctrl;
                        i2c_next_state_routine_block <= i2c_next_state_routine_block;
                        // de-assert flags
                        read_request_internal_flag <= 1'b0;
                        write_request_internal_flag <= 1'b0;
                    end
                end
                STATE_READ : begin
                    // Let's sample all the bits
                    if (rising_edge_detected == 1'b1 && iteration < 8) begin
                        // sample the data from sda input line
                        recv_data_buffer[7 - iteration] <= i2c_sda_in;
                        // increment the iteration counter to iterate through all bits
                        iteration <= iteration + 1'b1;
                        // keep the current state until the last bit
                        i2c_next_state_routine_block <= STATE_READ;
                    end
                    // When every bit has been sampled...
                    else if (rising_edge_detected == 1'b1 && iteration == 8) begin
                        if (register_addr_data_flag == 1'b0) begin
                            // reset the subroutine FSM
                            iteration <= 4'd0;
                            // give the proper ACK to the line
                            i2c_sda_out_pin_ctrl <= 1'b0;
                            i2c_next_state_routine_block <= STATE_READ;
                            received_data_internal_flag <= 1'b1;
                            register_addr_data_flag <= 1'b1;
                        end
                        else begin
                            // reset the subroutine FSM
                            iteration <= 4'd0;
                            // give the proper ACK to the line
                            i2c_sda_out_pin_ctrl <= 1'b0;
                            i2c_next_state_routine_block <= STATE_READ;
                            received_data_internal_flag <= 1'b1;
                            register_content_data_flag <= 1'b1;
                        end
                            
                    end 
                    else begin
                        // keep current state of all IO
                        iteration <= iteration;
                        i2c_sda_out_pin_ctrl <= i2c_sda_out_pin_ctrl;
                        i2c_next_state_routine_block <= i2c_next_state_routine_block;
                        // de-assert flag
                        received_data_internal_flag <= 1'b0;
                        register_addr_data_flag <= register_addr_data_flag;
                        register_content_data_flag <= register_content_data_flag;
                    end
                end
                STATE_WRITE : begin
                    if (rising_edge_detected == 1'b1 && iteration < 8) begin
                        i2c_sda_out_pin_ctrl <= i2c_sda_out_pin_ctrl;
                        // increment the iteration counter to iterate through all bits
                        iteration <= iteration + 1'b1;
                        // keep the current state until the last bit
                        i2c_next_state_routine_block <= STATE_WRITE;
                    end
                    else if (falling_edge_detected == 1'b1 && iteration < 8) begin
                        i2c_sda_out_pin_ctrl <= send_data_buffer[7-iteration];
                        iteration <= iteration;
                        i2c_next_state_routine_block <= i2c_next_state_routine_block;
                    end
                    else if (falling_edge_detected == 1'b1 && iteration == 8) begin
                        // release SDA line for ACK sampling
                        i2c_sda_out_pin_ctrl <= 1'b1;
                        iteration <= iteration;
                        i2c_next_state_routine_block <= i2c_next_state_routine_block;
                    end
                    // When every bit has been sampled...
                    else if (rising_edge_detected == 1'b1 && iteration == 8) begin
                        // if host is ACK (means still in write or keep sending data)
                        if (i2c_sda_in == 1'b0) begin
                            // reset the subroutine FSM
                            iteration <= 4'd0;
                            // set the flag
                            write_request_internal_flag <= 1'b1;
                            // Keep on WRITE
                            i2c_next_state_routine_block <= STATE_WRITE;
                        end
                        // if host NACK (usually this means terminating sequence) 
                        else begin
                            // reset the subroutine FSM
                            iteration <= 4'd0;
                            // de-assert flag
                            write_request_internal_flag <= 1'b0;
                            // return to IDLE state
                            i2c_next_state_routine_block <= STATE_IDLE;
                        end
                    end
                    else begin
                        // Keep current state of all IO, as well as de-assert flag
                        iteration <= iteration;
                        i2c_sda_out_pin_ctrl <= i2c_sda_out_pin_ctrl;
                        i2c_next_state_routine_block <= i2c_next_state_routine_block;
                        // de-assert flag
                        write_request_internal_flag <= 1'b0;
                    end
                end 
            endcase
        end
    end
            
    // The grand next state block, OR'ed from all the subroutine
    assign i2c_next_state = i2c_next_state_idle_block | i2c_next_state_routine_block;

    // Assigning SDA out control port complement to its true counterpart
    assign i2c_sda_out_pin_ctrl_n = ~i2c_sda_out_pin_ctrl;

    // Assign flags to ensure it is OR'ed, both read and write requests 
    // assign 

endmodule

// MASTER
// CLK_I
// RST_I
// ADDR_O[]
// DAT_I[]
// DAT_O[]
// CYC_O
// STB_O
// WE_O
// ACK_O
// ERR_O
// RTY_O

simulation/testbench_digital/i2c_tb.v
`timescale 10ns / 1ns

module i2c_tb;

    localparam SCL_PERIOD = 250;
    localparam WIDTH = 8;

    // Inputs for the module
    reg i2c_sda_in;
    reg i2c_scl_in;
    reg CLK_I;
    reg RST_I;
    reg [WIDTH-1:0] ADDR_I;
    reg [WIDTH-1:0] DAT_I;
    reg CYC_I;
    reg STB_I;
    reg WE_I;
    wire i2c_sda_out_pin_ctrl;
    wire i2c_sda_out_pin_ctrl_n;

    // Outputs for the module
    wire [WIDTH-1:0] DAT_O;
    wire ACK_O;
    wire ERR_O;
    wire RTY_O;

    i2c_controller #(.WIDTH(WIDTH)) my_controller (
        .i2c_sda_in(i2c_sda_in),
        .i2c_sda_out_pin_ctrl(i2c_sda_out_pin_ctrl),
        .i2c_sda_out_pin_ctrl_n(i2c_sda_out_pin_ctrl_n),
        .i2c_scl_in(i2c_scl_in),
        .CLK_I(CLK_I),
        .RST_I(RST_I),
        .ADDR_I(ADDR_I),
        .DAT_I(DAT_I),
        .CYC_I(CYC_I),
        .STB_I(STB_I),
        .WE_I(WE_I),
        .DAT_O(DAT_O),
        .ACK_O(ACK_O),
        .ERR_O(ERR_O),
        .RTY_O(RTY_O)
    );
    
    // I2C tasks
    task i2c_start;
    begin
        if (i2c_sda_in == 1'b1) begin
            wait (i2c_scl_in == 1'b0);
        end
        else begin
            i2c_sda_in <= 1;
            #(SCL_PERIOD/4);

        end
        wait (i2c_sda_in == 1'b1 && i2c_scl_in == 1'b1);
        // #(SCL_PERIOD/2);
        #(SCL_PERIOD/4);
        i2c_sda_in <= 0;
        #(SCL_PERIOD/2);
        // i2c_scl_in = 0;
    end
    endtask
    
    task i2c_stop;
    begin
        wait (i2c_scl_in == 1'b0);
        i2c_sda_in <= 0;
        wait (i2c_sda_in == 1'b0 && i2c_scl_in == 1'b1);
        // #(SCL_PERIOD/2);
        #(SCL_PERIOD/4);
        i2c_sda_in <= 1;
        #(SCL_PERIOD/2);
    end
    endtask
    
    task i2c_write_byte;
        input [7:0] data;
        input continue_cycle;
        integer i;
        begin
            for (i = 7; i >= 0; i--) begin
                i2c_sda_in <= data[i];
                #(SCL_PERIOD);
                // i2c_scl_in = 1;
                // #(SCL_PERIOD/2);
                // i2c_scl_in = 0;
            end
            // ACK phase (release SDA for slave)
            i2c_sda_in <= 1'b1;
            #(SCL_PERIOD);
            // i2c_scl_in = 1;
            // #(SCL_PERIOD/2);
            // i2c_scl_in = 0;
        end
    endtask

    task i2c_read_byte;
        output [7:0] data;
        input continue_cycle;
        integer i;
        begin
            for (i = 7; i >= 0; i--) begin
                data[i] = i2c_sda_out_pin_ctrl;
                #(SCL_PERIOD);
                // i2c_scl_in = 1;
                // #(SCL_PERIOD/2);
                // i2c_scl_in = 0;
            end
            // ACK phase (0 for keep slave sending, 1 for terminate)
            i2c_sda_in <= continue_cycle;
            #(SCL_PERIOD);
            // i2c_scl_in = 1;
            // #(SCL_PERIOD/2);
            // i2c_scl_in = 0;
        end
    endtask

    // WB Tasks
    task wb_write_register;
        input [7:0] target_addr;
        input [7:0] target_data;
        input continue_cycle;
        begin
            wait (CLK_I == 0);
            wait (CLK_I == 1);
            ADDR_I <= target_addr;
            DAT_I <= target_data;
            WE_I <= 1;
            STB_I <= 1;
            CYC_I <= 1;
            wait (CLK_I == 0);
            wait (CLK_I == 1);
            wait (CLK_I == 0);
            wait (CLK_I == 1);
            if (ACK_O == 1'b1) begin
                STB_I <= 0;
                CYC_I <= continue_cycle;
                WE_I <= 0;
                DAT_I <= 8'd0;
                ADDR_I <= 8'd0;
            end 
            else begin 
                target_data = 0;
                STB_I <= 0;
                CYC_I <= continue_cycle;
                WE_I <= 0;
                DAT_I <= 8'd0;
                ADDR_I <= 8'd0;
                $display("ERROR at writing to the register!!");
            end
        end
    endtask

    task wb_read_register;
        input [7:0] target_addr;
        output [7:0] target_data;
        input continue_cycle;
        begin
            wait (CLK_I == 0);
            wait (CLK_I == 1);
            ADDR_I <= target_addr;
            DAT_I <= 0;
            WE_I <= 0;
            STB_I <= 1;
            CYC_I <= 1;
            wait (CLK_I == 0);
            wait (CLK_I == 1);
            wait (CLK_I == 0);
            wait (CLK_I == 1);
            if (ACK_O == 1'b1) begin
                target_data = DAT_O;
                STB_I <= 0;
                CYC_I <= continue_cycle;
                WE_I <= 0;
                DAT_I <= 8'd0;
                ADDR_I <= 8'd0;
            end
            else begin 
                target_data <= 0;
                STB_I <= 0;
                CYC_I <= continue_cycle;
                WE_I <= 0;
                DAT_I <= 8'd0;
                ADDR_I <= 8'd0;
                $display("ERROR at reading the register!!");
            end
        end
    endtask
    
    reg [7:0] result;

    initial begin
        $dumpfile("i2c_result.vcd");
		$dumpvars(0, i2c_tb);
        i2c_sda_in = 1'b1;
        i2c_scl_in = 1'b1;
        CLK_I = 1'b0;
        RST_I = 1'b1;
        ADDR_I = 8'b0;
        DAT_I = 8'b0;
        CYC_I = 1'b0;
        STB_I = 1'b0;
        WE_I = 1'b0;
        #10;
        RST_I = 1'b0;
        #10;
    end

    always @(posedge CLK_I) begin
        wb_write_register(8'hA, 8'hAA, 1);
        wb_write_register(8'hC, 8'hAA, 0);
        // Write test
        $display("Reading from slave...");
        i2c_start();
        // I2C reading from device sequence
        i2c_write_byte(8'hAB,1);  // Address 0x55 + Read bit (1)
        i2c_read_byte(result,0);  // Data
        $display("Read result is %0h", result);
        
        $display("Writing to slave...");
        ///I2C writing to device sequence
        i2c_start();
        i2c_write_byte(8'hAA,1);  // Address 0x55 + Write bit (0)
        i2c_write_byte(8'hBE,1);  // Data
        wb_read_register(8'hB, result, 0);
        $display("Write result is %0h", result);
        i2c_stop();
        #1500;
        $finish;
    end

    assign i2c_sda_out_pin_ctrl_n = ~i2c_sda_out_pin_ctrl;
    always #5 CLK_I <= ~CLK_I;
    always #125 i2c_scl_in <= ~i2c_scl_in;
endmodule

i2c_result.vcd
$date
	Thu Jul 23 11:28:06 2026
$end
$version
	Icarus Verilog
$end
$timescale
	1ps
$end
$scope module i2c_tb $end
$var wire 1 ! i2c_sda_out_pin_ctrl_n $end
$var wire 1 " i2c_sda_out_pin_ctrl $end
$var wire 1 # RTY_O $end
$var wire 1 $ ERR_O $end
$var wire 8 % DAT_O [7:0] $end
$var wire 1 & ACK_O $end
$var parameter 32 ' SCL_PERIOD $end
$var parameter 32 ( WIDTH $end
$var reg 8 ) ADDR_I [7:0] $end
$var reg 1 * CLK_I $end
$var reg 1 + CYC_I $end
$var reg 8 , DAT_I [7:0] $end
$var reg 1 - RST_I $end
$var reg 1 . STB_I $end
$var reg 1 / WE_I $end
$var reg 1 0 i2c_scl_in $end
$var reg 1 1 i2c_sda_in $end
$var reg 8 2 result [7:0] $end
$scope module my_controller $end
$var wire 8 3 ADDR_I [7:0] $end
$var wire 1 * CLK_I $end
$var wire 1 + CYC_I $end
$var wire 8 4 DAT_I [7:0] $end
$var wire 1 - RST_I $end
$var wire 1 . STB_I $end
$var wire 1 / WE_I $end
$var wire 2 5 i2c_next_state [1:0] $end
$var wire 1 0 i2c_scl_in $end
$var wire 1 1 i2c_sda_in $end
$var wire 1 ! i2c_sda_out_pin_ctrl_n $end
$var wire 1 6 start_condition $end
$var wire 1 7 stop_condition $end
$var wire 1 8 falling_edge_detected_delayed $end
$var parameter 8 9 ADDR_SET_REGISTER_ADDRESS $end
$var parameter 8 : CTRL_STATUS_REGISTER_ADDRESS $end
$var parameter 8 ; RECV_DATA_BUFFER_ADDRESS $end
$var parameter 8 < SEND_DATA_BUFFER_ADDRESS $end
$var parameter 2 = STATE_ADDR $end
$var parameter 2 > STATE_IDLE $end
$var parameter 2 ? STATE_READ $end
$var parameter 2 @ STATE_WRITE $end
$var parameter 32 A WIDTH $end
$var reg 1 & ACK_O $end
$var reg 8 B DAT_O [7:0] $end
$var reg 1 $ ERR_O $end
$var reg 1 # RTY_O $end
$var reg 8 C addr_set_register [7:0] $end
$var reg 8 D address_data_buffer_internal [7:0] $end
$var reg 8 E ctrl_status_register [7:0] $end
$var reg 2 F falling_edge_delayer [1:0] $end
$var reg 1 G falling_edge_detected $end
$var reg 2 H i2c_next_state_idle_block [1:0] $end
$var reg 2 I i2c_next_state_routine_block [1:0] $end
$var reg 1 " i2c_sda_out_pin_ctrl $end
$var reg 2 J i2c_state [1:0] $end
$var reg 4 K iteration [3:0] $end
$var reg 1 L previous_state $end
$var reg 1 M read_request_internal_flag $end
$var reg 1 N received_data_internal_flag $end
$var reg 8 O recv_data_buffer [7:0] $end
$var reg 1 P rising_edge_detected $end
$var reg 1 Q sda_previous_state $end
$var reg 8 R send_data_buffer [7:0] $end
$var reg 1 S write_request_internal_flag $end
$upscope $end
$scope task i2c_read_byte $end
$var reg 1 T continue_cycle $end
$var reg 8 U data [7:0] $end
$var integer 32 V i [31:0] $end
$upscope $end
$scope task i2c_start $end
$upscope $end
$scope task i2c_stop $end
$upscope $end
$scope task i2c_write_byte $end
$var reg 1 W continue_cycle $end
$var reg 8 X data [7:0] $end
$var integer 32 Y i [31:0] $end
$upscope $end
$scope task wb_read_register $end
$var reg 1 Z continue_cycle $end
$var reg 8 [ target_addr [7:0] $end
$var reg 8 \ target_data [7:0] $end
$upscope $end
$scope task wb_write_register $end
$var reg 1 ] continue_cycle $end
$var reg 8 ^ target_addr [7:0] $end
$var reg 8 _ target_data [7:0] $end
$upscope $end
$upscope $end
$enddefinitions $end
$comment Show the parameter values. $end
$dumpall
b1000 A
b11 @
b10 ?
b0 >
b1 =
b1100 <
b1011 ;
b1101 :
b1010 9
b1000 (
b11111010 '
$end
#0
$dumpvars
bx _
bx ^
x]
bx \
bx [
xZ
bx Y
bx X
xW
bx V
bx U
xT
xS
bx R
xQ
xP
bx O
xN
xM
xL
bx K
bx J
bx I
b0 H
xG
bx F
bx E
bx D
bx C
bx B
x8
x7
06
bx 5
b0 4
b0 3
bx 2
11
10
0/
0.
1-
b0 ,
0+
0*
b0 )
x&
bx %
x$
x#
x"
x!
$end
#50000
17
b0 5
0#
0&
0$
b0 %
b0 B
0Q
0G
0L
b0 J
b0 K
b0 I
1]
b10101010 _
b1010 ^
1*
#100000
0*
0-
#150000
07
1P
1L
1Q
1+
1.
1/
b10101010 ,
b10101010 4
b1010 )
b1010 3
1*
#200000
0*
#250000
1&
b10101010 C
0P
1*
#300000
0*
#350000
0&
b0 )
b0 3
b0 ,
b0 4
0/
0.
0]
b1100 ^
1*
#400000
0*
#450000
1.
1/
b10101010 ,
b10101010 4
b1100 )
b1100 3
1*
#500000
0*
#550000
1&
b10101010 R
1*
#600000
0*
#650000
0&
b0 )
b0 3
b0 ,
b0 4
0/
0+
0.
1*
#700000
0*
#750000
1*
#800000
0*
#850000
1*
#900000
0*
#950000
1*
#1000000
0*
#1050000
1*
#1100000
0*
#1150000
1*
#1200000
0*
#1250000
1G
0L
1*
00
#1300000
0*
#1350000
0G
1*
#1400000
0*
#1450000
1*
#1500000
0*
#1550000
1*
#1600000
0*
#1650000
1*
#1700000
0*
#1750000
1*
#1800000
0*
#1850000
1*
#1900000
0*
#1950000
1*
#2000000
0*
#2050000
1*
#2100000
0*
#2150000
1*
#2200000
0*
#2250000
1*
#2300000
0*
#2350000
1*
#2400000
0*
#2450000
1*
#2500000
0*
10
#2550000
1P
1L
1*
#2600000
0*
#2650000
0P
1*
#2700000
0*
#2750000
1*
#2800000
0*
#2850000
1*
#2900000
0*
#2950000
1*
#3000000
0*
#3050000
1*
#3100000
0*
#3120000
b1 5
b1 H
16
01
#3150000
06
b0 H
b1 I
b1 J
0Q
1*
#3200000
0*
#3250000
0S
0M
1*
#3300000
0*
#3350000
1*
#3400000
0*
#3450000
1*
#3500000
0*
#3550000
1*
#3600000
0*
#3650000
1*
#3700000
0*
#3750000
1G
0L
1*
00
#3800000
0*
#3850000
0G
1*
#3900000
0*
#3950000
1*
#4000000
0*
#4050000
1*
#4100000
0*
#4150000
1*
#4200000
0*
#4250000
1*
#4300000
0*
#4350000
1*
#4370000
11
b111 Y
1W
b10101011 X
#4400000
0*
#4450000
1Q
1*
#4500000
0*
#4550000
1*
#4600000
0*
#4650000
1*
#4700000
0*
#4750000
1*
#4800000
0*
#4850000
1*
#4900000
0*
#4950000
1*
#5000000
0*
10
#5050000
1P
1L
1*
#5100000
0*
#5150000
b1 K
b1xxxxxxx D
0P
1*
#5200000
0*
#5250000
1*
#5300000
0*
#5350000
1*
#5400000
0*
#5450000
1*
#5500000
0*
#5550000
1*
#5600000
0*
#5650000
1*
#5700000
0*
#5750000
1*
#5800000
0*
#5850000
1*
#5900000
0*
#5950000
1*
#6000000
0*
#6050000
1*
#6100000
0*
#6150000
1*
#6200000
0*
#6250000
1G
0L
1*
00
#6300000
0*
#6350000
0G
1*
#6400000
0*
#6450000
1*
#6500000
0*
#6550000
1*
#6600000
0*
#6650000
1*
#6700000
0*
#6750000
1*
#6800000
0*
#6850000
1*
#6870000
01
b110 Y
#6900000
0*
#6950000
0Q
1*
#7000000
0*
#7050000
1*
#7100000
0*
#7150000
1*
#7200000
0*
#7250000
1*
#7300000
0*
#7350000
1*
#7400000
0*
#7450000
1*
#7500000
0*
10
#7550000
1P
1L
1*
#7600000
0*
#7650000
0P
b10 K
b10xxxxxx D
1*
#7700000
0*
#7750000
1*
#7800000
0*
#7850000
1*
#7900000
0*
#7950000
1*
#8000000
0*
#8050000
1*
#8100000
0*
#8150000
1*
#8200000
0*
#8250000
1*
#8300000
0*
#8350000
1*
#8400000
0*
#8450000
1*
#8500000
0*
#8550000
1*
#8600000
0*
#8650000
1*
#8700000
0*
#8750000
1G
0L
1*
00
#8800000
0*
#8850000
0G
1*
#8900000
0*
#8950000
1*
#9000000
0*
#9050000
1*
#9100000
0*
#9150000
1*
#9200000
0*
#9250000
1*
#9300000
0*
#9350000
1*
#9370000
11
b101 Y
#9400000
0*
#9450000
1Q
1*
#9500000
0*
#9550000
1*
#9600000
0*
#9650000
1*
#9700000
0*
#9750000
1*
#9800000
0*
#9850000
1*
#9900000
0*
#9950000
1*
#10000000
0*
10
#10050000
1P
1L
1*
#10100000
0*
#10150000
b11 K
b101xxxxx D
0P
1*
#10200000
0*
#10250000
1*
#10300000
0*
#10350000
1*
#10400000
0*
#10450000
1*
#10500000
0*
#10550000
1*
#10600000
0*
#10650000
1*
#10700000
0*
#10750000
1*
#10800000
0*
#10850000
1*
#10900000
0*
#10950000
1*
#11000000
0*
#11050000
1*
#11100000
0*
#11150000
1*
#11200000
0*
#11250000
1G
0L
1*
00
#11300000
0*
#11350000
0G
1*
#11400000
0*
#11450000
1*
#11500000
0*
#11550000
1*
#11600000
0*
#11650000
1*
#11700000
0*
#11750000
1*
#11800000
0*
#11850000
1*
#11870000
01
b100 Y
#11900000
0*
#11950000
0Q
1*
#12000000
0*
#12050000
1*
#12100000
0*
#12150000
1*
#12200000
0*
#12250000
1*
#12300000
0*
#12350000
1*
#12400000
0*
#12450000
1*
#12500000
0*
10
#12550000
1P
1L
1*
#12600000
0*
#12650000
0P
b100 K
b1010xxxx D
1*
#12700000
0*
#12750000
1*
#12800000
0*
#12850000
1*
#12900000
0*
#12950000
1*
#13000000
0*
#13050000
1*
#13100000
0*
#13150000
1*
#13200000
0*
#13250000
1*
#13300000
0*
#13350000
1*
#13400000
0*
#13450000
1*
#13500000
0*
#13550000
1*
#13600000
0*
#13650000
1*
#13700000
0*
#13750000
1G
0L
1*
00
#13800000
0*
#13850000
0G
1*
#13900000
0*
#13950000
1*
#14000000
0*
#14050000
1*
#14100000
0*
#14150000
1*
#14200000
0*
#14250000
1*
#14300000
0*
#14350000
1*
#14370000
11
b11 Y
#14400000
0*
#14450000
1Q
1*
#14500000
0*
#14550000
1*
#14600000
0*
#14650000
1*
#14700000
0*
#14750000
1*
#14800000
0*
#14850000
1*
#14900000
0*
#14950000
1*
#15000000
0*
10
#15050000
1P
1L
1*
#15100000
0*
#15150000
b101 K
b10101xxx D
0P
1*
#15200000
0*
#15250000
1*
#15300000
0*
#15350000
1*
#15400000
0*
#15450000
1*
#15500000
0*
#15550000
1*
#15600000
0*
#15650000
1*
#15700000
0*
#15750000
1*
#15800000
0*
#15850000
1*
#15900000
0*
#15950000
1*
#16000000
0*
#16050000
1*
#16100000
0*
#16150000
1*
#16200000
0*
#16250000
1G
0L
1*
00
#16300000
0*
#16350000
0G
1*
#16400000
0*
#16450000
1*
#16500000
0*
#16550000
1*
#16600000
0*
#16650000
1*
#16700000
0*
#16750000
1*
#16800000
0*
#16850000
1*
#16870000
01
b10 Y
#16900000
0*
#16950000
0Q
1*
#17000000
0*
#17050000
1*
#17100000
0*
#17150000
1*
#17200000
0*
#17250000
1*
#17300000
0*
#17350000
1*
#17400000
0*
#17450000
1*
#17500000
0*
10
#17550000
1P
1L
1*
#17600000
0*
#17650000
0P
b110 K
b101010xx D
1*
#17700000
0*
#17750000
1*
#17800000
0*
#17850000
1*
#17900000
0*
#17950000
1*
#18000000
0*
#18050000
1*
#18100000
0*
#18150000
1*
#18200000
0*
#18250000
1*
#18300000
0*
#18350000
1*
#18400000
0*
#18450000
1*
#18500000
0*
#18550000
1*
